quickboard/__init__.py
quickboard/app.py
quickboard/styles.py
quickboard/base/__init__.py
quickboard/base/_dynamicpanel.py
quickboard/base/basetab.py
quickboard/base/contentgrid.py
quickboard/base/datapanel.py
quickboard/base/plotpanel.py
quickboard/base/quickboard.py
quickboard/base/sidebar.py
quickboard/plugins/__init__.py
quickboard/plugins/datadisplay.py
quickboard/plugins/datafilterchecklist.py
quickboard/plugins/datafilterdropdown.py
quickboard/plugins/datafilterradiobuttons.py
quickboard/plugins/datafilterrangeslider.py
quickboard/plugins/datafilterslider.py
quickboard/plugins/datasumchecklist.py
quickboard/plugins/plotinputdropdown.py
quickboard/plugins/plotinputradiobuttons.py
quickboard/plugins/plotinputrangeslider.py
quickboard/plugins/plotinputslider.py
quickboard/plugins/templates/__init__.py
quickboard/plugins/templates/checklist.py
quickboard/plugins/templates/dropdown.py
quickboard/plugins/templates/radiobuttons.py
quickboard/plugins/templates/rangeslider.py
quickboard/plugins/templates/slider.py
quickboard/primitives/__init__.py
quickboard/primitives/_datamanager.py
quickboard/primitives/_panel.py
quickboard/primitives/controlplugin.py
quickboard/textboxes/__init__.py
quickboard/textboxes/getupdatedtext.py
quickboard/utils/__init__.py
quickboard/utils/decorators.py
quickboard-0.4.1.dist-info/licenses/LICENSE
test/__init__.py
test/run_tests.py
test/test_template.py
quickboard-0.4.1.dist-info/METADATA
quickboard-0.4.1.dist-info/WHEEL
quickboard-0.4.1.dist-info/top_level.txt
quickboard-0.4.1.dist-info/RECORD
