Metadata-Version: 2.4
Name: quickboard
Version: 0.4.1
Summary: "A simple Python package for creating quick, modular dashboards."
Home-page: https://github.com/rickymagner/quickboard
Download-URL: https://github.com/rickymagner/quickboard
Author: Ricky Magner
Author-email: rmagner@bu.edu
Keywords: dash,dashboard,interactive,plot,graph
Classifier: Framework :: Dash
Classifier: License :: OSI Approved :: BSD License
Classifier: Programming Language :: Python
License-File: LICENSE
Requires-Dist: dash>=2.16.0
Requires-Dist: dash_bootstrap_components>=1.5.0
Requires-Dist: plotly>=5.20.0
Requires-Dist: numpy>=1.25.0
Requires-Dist: pandas>=2.2.1
Dynamic: download-url
Dynamic: license-file
